MANIFEST.in
account_view.xml
l10n_br_wizard.xml
setup.py
./__init__.py
./__openerp__.py
./account.py
data/account.account.template.csv
data/account.account.type.csv
data/account_chart_template.xml
data/account_tax_code_template.xml
data/account_tax_template.xml
i18n/ar.po
i18n/bg.po
i18n/ca.po
i18n/da.po
i18n/en_GB.po
i18n/es.po
i18n/es_CR.po
i18n/es_MX.po
i18n/es_PY.po
i18n/es_VE.po
i18n/fr.po
i18n/gl.po
i18n/hi.po
i18n/it.po
i18n/l10n_br.pot
i18n/nb.po
i18n/nl.po
i18n/oc.po
i18n/pt.po
i18n/pt_BR.po
i18n/ru.po
i18n/sl.po
i18n/sq.po
i18n/sr@latin.po
i18n/tr.po
images/1_config_chart_l10n_br.jpeg
images/2_l10n_br_chart.jpeg
openerp_l10n_br.egg-info/PKG-INFO
openerp_l10n_br.egg-info/SOURCES.txt
openerp_l10n_br.egg-info/dependency_links.txt
openerp_l10n_br.egg-info/requires.txt
openerp_l10n_br.egg-info/top_level.txt
static/src/img/icon.png